{"tier":"Axi","name":"D4","rewards":{"Intact":[{"_id":"0f83aea6354c0cad2b224d4f2a4f5f6a","itemName":"Dakra Prime Blade","rarity":"Rare","chance":2},{"_id":"e1457a0ff9a34fb1c1c570c707a1d566","itemName":"Boar Prime Barrel","rarity":"Uncommon","chance":11},{"_id":"387d3a0f2e4acabbbb5abea437d1a95a","itemName":"Mag Prime Neuroptics Blueprint","rarity":"Uncommon","chance":11},{"_id":"92cbd63c98866a7f2a21b0eec73bcc5c","itemName":"Latron Prime Barrel","rarity":"Uncommon","chance":25.33},{"_id":"f78233e68e6995715c0935c66b1aff1b","itemName":"Frost Prime Neuroptics Blueprint","rarity":"Uncommon","chance":25.33},{"_id":"f1d3923651587359f9444f183330e4c2","itemName":"Forma Blueprint","rarity":"Uncommon","chance":25.33}],"Exceptional":[{"_id":"0f83aea6354c0cad2b224d4f2a4f5f6a","itemName":"Dakra Prime Blade","rarity":"Rare","chance":4},{"_id":"e1457a0ff9a34fb1c1c570c707a1d566","itemName":"Boar Prime Barrel","rarity":"Uncommon","chance":13},{"_id":"387d3a0f2e4acabbbb5abea437d1a95a","itemName":"Mag Prime Neuroptics Blueprint","rarity":"Uncommon","chance":13},{"_id":"92cbd63c98866a7f2a21b0eec73bcc5c","itemName":"Latron Prime Barrel","rarity":"Uncommon","chance":23.33},{"_id":"f78233e68e6995715c0935c66b1aff1b","itemName":"Frost Prime Neuroptics Blueprint","rarity":"Uncommon","chance":23.33},{"_id":"f1d3923651587359f9444f183330e4c2","itemName":"Forma Blueprint","rarity":"Uncommon","chance":23.33}],"Flawless":[{"_id":"0f83aea6354c0cad2b224d4f2a4f5f6a","itemName":"Dakra Prime Blade","rarity":"Rare","chance":6},{"_id":"e1457a0ff9a34fb1c1c570c707a1d566","itemName":"Boar Prime Barrel","rarity":"Uncommon","chance":17},{"_id":"387d3a0f2e4acabbbb5abea437d1a95a","itemName":"Mag Prime Neuroptics Blueprint","rarity":"Uncommon","chance":17},{"_id":"92cbd63c98866a7f2a21b0eec73bcc5c","itemName":"Latron Prime Barrel","rarity":"Uncommon","chance":20},{"_id":"f78233e68e6995715c0935c66b1aff1b","itemName":"Frost Prime Neuroptics Blueprint","rarity":"Uncommon","chance":20},{"_id":"f1d3923651587359f9444f183330e4c2","itemName":"Forma Blueprint","rarity":"Uncommon","chance":20}],"Radiant":[{"_id":"0f83aea6354c0cad2b224d4f2a4f5f6a","itemName":"Dakra Prime Blade","rarity":"Uncommon","chance":10},{"_id":"e1457a0ff9a34fb1c1c570c707a1d566","itemName":"Boar Prime Barrel","rarity":"Uncommon","chance":20},{"_id":"387d3a0f2e4acabbbb5abea437d1a95a","itemName":"Mag Prime Neuroptics Blueprint","rarity":"Uncommon","chance":20},{"_id":"92cbd63c98866a7f2a21b0eec73bcc5c","itemName":"Latron Prime Barrel","rarity":"Uncommon","chance":16.67},{"_id":"f78233e68e6995715c0935c66b1aff1b","itemName":"Frost Prime Neuroptics Blueprint","rarity":"Uncommon","chance":16.67},{"_id":"f1d3923651587359f9444f183330e4c2","itemName":"Forma Blueprint","rarity":"Uncommon","chance":16.67}]}}