{"tier":"Axi","name":"M3","rewards":{"Intact":[{"_id":"4780108a5de91e08c35da5f85fee733f","itemName":"Mesa Prime Neuroptics Blueprint","rarity":"Rare","chance":2},{"_id":"dc99d42f71072b73f8cc5fb6969480bf","itemName":"Hydroid Prime Neuroptics Blueprint","rarity":"Uncommon","chance":11},{"_id":"2f0112dbba02975241218b20bbaaa2d7","itemName":"Ballistica Prime Upper Limb","rarity":"Uncommon","chance":11},{"_id":"060778aeaf438d5db7db8f38a35ced38","itemName":"Akjagara Prime Blueprint","rarity":"Uncommon","chance":25.33},{"_id":"371732a7c5612bde4c88027a2224814d","itemName":"Fang Prime Blade","rarity":"Uncommon","chance":25.33},{"_id":"f1d3923651587359f9444f183330e4c2","itemName":"Forma Blueprint","rarity":"Uncommon","chance":25.33}],"Exceptional":[{"_id":"4780108a5de91e08c35da5f85fee733f","itemName":"Mesa Prime Neuroptics Blueprint","rarity":"Rare","chance":4},{"_id":"dc99d42f71072b73f8cc5fb6969480bf","itemName":"Hydroid Prime Neuroptics Blueprint","rarity":"Uncommon","chance":13},{"_id":"2f0112dbba02975241218b20bbaaa2d7","itemName":"Ballistica Prime Upper Limb","rarity":"Uncommon","chance":13},{"_id":"060778aeaf438d5db7db8f38a35ced38","itemName":"Akjagara Prime Blueprint","rarity":"Uncommon","chance":23.33},{"_id":"371732a7c5612bde4c88027a2224814d","itemName":"Fang Prime Blade","rarity":"Uncommon","chance":23.33},{"_id":"f1d3923651587359f9444f183330e4c2","itemName":"Forma Blueprint","rarity":"Uncommon","chance":23.33}],"Flawless":[{"_id":"4780108a5de91e08c35da5f85fee733f","itemName":"Mesa Prime Neuroptics Blueprint","rarity":"Rare","chance":6},{"_id":"dc99d42f71072b73f8cc5fb6969480bf","itemName":"Hydroid Prime Neuroptics Blueprint","rarity":"Uncommon","chance":17},{"_id":"2f0112dbba02975241218b20bbaaa2d7","itemName":"Ballistica Prime Upper Limb","rarity":"Uncommon","chance":17},{"_id":"060778aeaf438d5db7db8f38a35ced38","itemName":"Akjagara Prime Blueprint","rarity":"Uncommon","chance":20},{"_id":"371732a7c5612bde4c88027a2224814d","itemName":"Fang Prime Blade","rarity":"Uncommon","chance":20},{"_id":"f1d3923651587359f9444f183330e4c2","itemName":"Forma Blueprint","rarity":"Uncommon","chance":20}],"Radiant":[{"_id":"4780108a5de91e08c35da5f85fee733f","itemName":"Mesa Prime Neuroptics Blueprint","rarity":"Uncommon","chance":10},{"_id":"dc99d42f71072b73f8cc5fb6969480bf","itemName":"Hydroid Prime Neuroptics Blueprint","rarity":"Uncommon","chance":20},{"_id":"2f0112dbba02975241218b20bbaaa2d7","itemName":"Ballistica Prime Upper Limb","rarity":"Uncommon","chance":20},{"_id":"060778aeaf438d5db7db8f38a35ced38","itemName":"Akjagara Prime Blueprint","rarity":"Uncommon","chance":16.67},{"_id":"371732a7c5612bde4c88027a2224814d","itemName":"Fang Prime Blade","rarity":"Uncommon","chance":16.67},{"_id":"f1d3923651587359f9444f183330e4c2","itemName":"Forma Blueprint","rarity":"Uncommon","chance":16.67}]}}