{"tier":"Lith","name":"N1","rewards":{"Intact":[{"itemName":"Nova Prime Chassis Blueprint","rarity":"Rare","chance":2},{"itemName":"Akbronco Prime Link","rarity":"Uncommon","chance":11},{"itemName":"Forma Blueprint","rarity":"Uncommon","chance":11},{"itemName":"Nekros Prime Chassis Blueprint","rarity":"Uncommon","chance":25.33},{"itemName":"Bronco Prime Blueprint","rarity":"Uncommon","chance":25.33},{"itemName":"Fang Prime Blade","rarity":"Uncommon","chance":25.33}],"Exceptional":[{"itemName":"Nova Prime Chassis Blueprint","rarity":"Rare","chance":4},{"itemName":"Akbronco Prime Link","rarity":"Uncommon","chance":13},{"itemName":"Forma Blueprint","rarity":"Uncommon","chance":13},{"itemName":"Nekros Prime Chassis Blueprint","rarity":"Uncommon","chance":23.33},{"itemName":"Bronco Prime Blueprint","rarity":"Uncommon","chance":23.33},{"itemName":"Fang Prime Blade","rarity":"Uncommon","chance":23.33}],"Flawless":[{"itemName":"Nova Prime Chassis Blueprint","rarity":"Rare","chance":6},{"itemName":"Akbronco Prime Link","rarity":"Uncommon","chance":17},{"itemName":"Forma Blueprint","rarity":"Uncommon","chance":17},{"itemName":"Nekros Prime Chassis Blueprint","rarity":"Uncommon","chance":20},{"itemName":"Bronco Prime Blueprint","rarity":"Uncommon","chance":20},{"itemName":"Fang Prime Blade","rarity":"Uncommon","chance":20}],"Radiant":[{"itemName":"Nova Prime Chassis Blueprint","rarity":"Uncommon","chance":10},{"itemName":"Akbronco Prime Link","rarity":"Uncommon","chance":20},{"itemName":"Forma Blueprint","rarity":"Uncommon","chance":20},{"itemName":"Nekros Prime Chassis Blueprint","rarity":"Uncommon","chance":16.67},{"itemName":"Bronco Prime Blueprint","rarity":"Uncommon","chance":16.67},{"itemName":"Fang Prime Blade","rarity":"Uncommon","chance":16.67}]}}