{"tier":"Lith","name":"N5","rewards":{"Intact":[{"_id":"7423fdc4254a1f14163f9c129983b2b9","itemName":"Ninkondi Prime Handle","rarity":"Rare","chance":2},{"_id":"2f6b636a17276cb64d25a298d91e4c8c","itemName":"Braton Prime Receiver","rarity":"Uncommon","chance":11},{"_id":"5693ebd425aa46d291566f2c7a9a1b1c","itemName":"Ivara Prime Blueprint","rarity":"Uncommon","chance":11},{"_id":"b30341301002db94cb566d13b3f2efb1","itemName":"Stradavar Prime Stock","rarity":"Uncommon","chance":25.33},{"_id":"99b4c1b335006fd383a17fc6eec4017d","itemName":"Zhuge Prime String","rarity":"Uncommon","chance":25.33},{"_id":"f1d3923651587359f9444f183330e4c2","itemName":"Forma Blueprint","rarity":"Uncommon","chance":25.33}],"Exceptional":[{"_id":"7423fdc4254a1f14163f9c129983b2b9","itemName":"Ninkondi Prime Handle","rarity":"Rare","chance":4},{"_id":"2f6b636a17276cb64d25a298d91e4c8c","itemName":"Braton Prime Receiver","rarity":"Uncommon","chance":13},{"_id":"5693ebd425aa46d291566f2c7a9a1b1c","itemName":"Ivara Prime Blueprint","rarity":"Uncommon","chance":13},{"_id":"b30341301002db94cb566d13b3f2efb1","itemName":"Stradavar Prime Stock","rarity":"Uncommon","chance":23.33},{"_id":"99b4c1b335006fd383a17fc6eec4017d","itemName":"Zhuge Prime String","rarity":"Uncommon","chance":23.33},{"_id":"f1d3923651587359f9444f183330e4c2","itemName":"Forma Blueprint","rarity":"Uncommon","chance":23.33}],"Flawless":[{"_id":"7423fdc4254a1f14163f9c129983b2b9","itemName":"Ninkondi Prime Handle","rarity":"Rare","chance":6},{"_id":"2f6b636a17276cb64d25a298d91e4c8c","itemName":"Braton Prime Receiver","rarity":"Uncommon","chance":17},{"_id":"5693ebd425aa46d291566f2c7a9a1b1c","itemName":"Ivara Prime Blueprint","rarity":"Uncommon","chance":17},{"_id":"b30341301002db94cb566d13b3f2efb1","itemName":"Stradavar Prime Stock","rarity":"Uncommon","chance":20},{"_id":"99b4c1b335006fd383a17fc6eec4017d","itemName":"Zhuge Prime String","rarity":"Uncommon","chance":20},{"_id":"f1d3923651587359f9444f183330e4c2","itemName":"Forma Blueprint","rarity":"Uncommon","chance":20}],"Radiant":[{"_id":"7423fdc4254a1f14163f9c129983b2b9","itemName":"Ninkondi Prime Handle","rarity":"Uncommon","chance":10},{"_id":"2f6b636a17276cb64d25a298d91e4c8c","itemName":"Braton Prime Receiver","rarity":"Uncommon","chance":20},{"_id":"5693ebd425aa46d291566f2c7a9a1b1c","itemName":"Ivara Prime Blueprint","rarity":"Uncommon","chance":20},{"_id":"b30341301002db94cb566d13b3f2efb1","itemName":"Stradavar Prime Stock","rarity":"Uncommon","chance":16.67},{"_id":"99b4c1b335006fd383a17fc6eec4017d","itemName":"Zhuge Prime String","rarity":"Uncommon","chance":16.67},{"_id":"f1d3923651587359f9444f183330e4c2","itemName":"Forma Blueprint","rarity":"Uncommon","chance":16.67}]}}