{"tier":"Meso","name":"A5","rewards":{"Intact":[{"_id":"bd46fc1a74c1c99ab91e6d3374e81d92","itemName":"Acceltra Prime Barrel","rarity":"Rare","chance":2},{"_id":"7141ed9b3226f56cec8f3a7d2e8721aa","itemName":"Fulmin Prime Blueprint","rarity":"Uncommon","chance":11},{"_id":"70323258b934fc228b5dce835f86490b","itemName":"Afuris Prime Link","rarity":"Uncommon","chance":11},{"_id":"bd60f5414db72b77df25741fb54ccad1","itemName":"Akbronco Prime Blueprint","rarity":"Uncommon","chance":25.33},{"_id":"3dd7525263074b65c685dbbcbf0a50db","itemName":"Grendel Prime Neuroptics Blueprint","rarity":"Uncommon","chance":25.33},{"_id":"c6508ab756b77fcfbd462008d53c8396","itemName":"Khora Prime Systems Blueprint","rarity":"Uncommon","chance":25.33}],"Exceptional":[{"_id":"bd46fc1a74c1c99ab91e6d3374e81d92","itemName":"Acceltra Prime Barrel","rarity":"Rare","chance":4},{"_id":"7141ed9b3226f56cec8f3a7d2e8721aa","itemName":"Fulmin Prime Blueprint","rarity":"Uncommon","chance":13},{"_id":"70323258b934fc228b5dce835f86490b","itemName":"Afuris Prime Link","rarity":"Uncommon","chance":13},{"_id":"bd60f5414db72b77df25741fb54ccad1","itemName":"Akbronco Prime Blueprint","rarity":"Uncommon","chance":23.33},{"_id":"3dd7525263074b65c685dbbcbf0a50db","itemName":"Grendel Prime Neuroptics Blueprint","rarity":"Uncommon","chance":23.33},{"_id":"c6508ab756b77fcfbd462008d53c8396","itemName":"Khora Prime Systems Blueprint","rarity":"Uncommon","chance":23.33}],"Flawless":[{"_id":"bd46fc1a74c1c99ab91e6d3374e81d92","itemName":"Acceltra Prime Barrel","rarity":"Rare","chance":6},{"_id":"7141ed9b3226f56cec8f3a7d2e8721aa","itemName":"Fulmin Prime Blueprint","rarity":"Uncommon","chance":17},{"_id":"70323258b934fc228b5dce835f86490b","itemName":"Afuris Prime Link","rarity":"Uncommon","chance":17},{"_id":"bd60f5414db72b77df25741fb54ccad1","itemName":"Akbronco Prime Blueprint","rarity":"Uncommon","chance":20},{"_id":"3dd7525263074b65c685dbbcbf0a50db","itemName":"Grendel Prime Neuroptics Blueprint","rarity":"Uncommon","chance":20},{"_id":"c6508ab756b77fcfbd462008d53c8396","itemName":"Khora Prime Systems Blueprint","rarity":"Uncommon","chance":20}],"Radiant":[{"_id":"bd46fc1a74c1c99ab91e6d3374e81d92","itemName":"Acceltra Prime Barrel","rarity":"Uncommon","chance":10},{"_id":"7141ed9b3226f56cec8f3a7d2e8721aa","itemName":"Fulmin Prime Blueprint","rarity":"Uncommon","chance":20},{"_id":"70323258b934fc228b5dce835f86490b","itemName":"Afuris Prime Link","rarity":"Uncommon","chance":20},{"_id":"bd60f5414db72b77df25741fb54ccad1","itemName":"Akbronco Prime Blueprint","rarity":"Uncommon","chance":16.67},{"_id":"3dd7525263074b65c685dbbcbf0a50db","itemName":"Grendel Prime Neuroptics Blueprint","rarity":"Uncommon","chance":16.67},{"_id":"c6508ab756b77fcfbd462008d53c8396","itemName":"Khora Prime Systems Blueprint","rarity":"Uncommon","chance":16.67}]}}