{"tier":"Meso","name":"K3","rewards":{"Intact":[{"_id":"fd7d42539d58167639e8feedf42d4fbd","itemName":"Karyst Prime Blade","rarity":"Rare","chance":2},{"_id":"f1d3923651587359f9444f183330e4c2","itemName":"Forma Blueprint","rarity":"Uncommon","chance":11},{"_id":"a00aa39b585a51f46205ded5c971e7f5","itemName":"Wukong Prime Chassis Blueprint","rarity":"Uncommon","chance":11},{"_id":"21a7b38b1e9d198cd39993a7154e0ea9","itemName":"Ninkondi Prime Blueprint","rarity":"Uncommon","chance":25.33},{"_id":"c16dafff7a71a6898079dc3d54921068","itemName":"Orthos Prime Handle","rarity":"Uncommon","chance":25.33},{"_id":"c534d3c6c7c29b9891620a6411234912","itemName":"Braton Prime Stock","rarity":"Uncommon","chance":25.33}],"Exceptional":[{"_id":"fd7d42539d58167639e8feedf42d4fbd","itemName":"Karyst Prime Blade","rarity":"Rare","chance":4},{"_id":"f1d3923651587359f9444f183330e4c2","itemName":"Forma Blueprint","rarity":"Uncommon","chance":13},{"_id":"a00aa39b585a51f46205ded5c971e7f5","itemName":"Wukong Prime Chassis Blueprint","rarity":"Uncommon","chance":13},{"_id":"21a7b38b1e9d198cd39993a7154e0ea9","itemName":"Ninkondi Prime Blueprint","rarity":"Uncommon","chance":23.33},{"_id":"c16dafff7a71a6898079dc3d54921068","itemName":"Orthos Prime Handle","rarity":"Uncommon","chance":23.33},{"_id":"c534d3c6c7c29b9891620a6411234912","itemName":"Braton Prime Stock","rarity":"Uncommon","chance":23.33}],"Flawless":[{"_id":"fd7d42539d58167639e8feedf42d4fbd","itemName":"Karyst Prime Blade","rarity":"Rare","chance":6},{"_id":"f1d3923651587359f9444f183330e4c2","itemName":"Forma Blueprint","rarity":"Uncommon","chance":17},{"_id":"a00aa39b585a51f46205ded5c971e7f5","itemName":"Wukong Prime Chassis Blueprint","rarity":"Uncommon","chance":17},{"_id":"21a7b38b1e9d198cd39993a7154e0ea9","itemName":"Ninkondi Prime Blueprint","rarity":"Uncommon","chance":20},{"_id":"c16dafff7a71a6898079dc3d54921068","itemName":"Orthos Prime Handle","rarity":"Uncommon","chance":20},{"_id":"c534d3c6c7c29b9891620a6411234912","itemName":"Braton Prime Stock","rarity":"Uncommon","chance":20}],"Radiant":[{"_id":"fd7d42539d58167639e8feedf42d4fbd","itemName":"Karyst Prime Blade","rarity":"Uncommon","chance":10},{"_id":"f1d3923651587359f9444f183330e4c2","itemName":"Forma Blueprint","rarity":"Uncommon","chance":20},{"_id":"a00aa39b585a51f46205ded5c971e7f5","itemName":"Wukong Prime Chassis Blueprint","rarity":"Uncommon","chance":20},{"_id":"21a7b38b1e9d198cd39993a7154e0ea9","itemName":"Ninkondi Prime Blueprint","rarity":"Uncommon","chance":16.67},{"_id":"c16dafff7a71a6898079dc3d54921068","itemName":"Orthos Prime Handle","rarity":"Uncommon","chance":16.67},{"_id":"c534d3c6c7c29b9891620a6411234912","itemName":"Braton Prime Stock","rarity":"Uncommon","chance":16.67}]}}